{
  "id": "10316",
  "name": "THE LORD OF THE RINGS: RIVENDELL™",
  "themeId": "1068",
  "themeName": "LEGO Icons",
  "yearReleased": 2023,
  "weight": 6890,
  "price": 499.99,
  "pieces": 6167,
  "vipPoints": 3250,
  "hardToFind": false,
  "availabilityId": "1",
  "availability": "Available now",
  "description": "Journey into Rivendell™ with this LEGO® The Lord of the Rings™ collectible (10316). Based on the Middle-earth™ valley where the famous quest began, this impressive 6,167-piece project for adults is bursting with details that movie fans will adore.",
  "heightCentimeters": 39,
  "heightInches": 16,
  "widthCentimeters": 72,
  "widthInches": 29,
  "depthCentimeters": 50,
  "depthInches": 20
}